[{
    "master": "001",
    "slave": "001-01"
},
{
    "master": "001",
    "slave": "001-02"
},
{
    "master": "001",
    "slave": "001-03"
},
{
    "master": "001",
    "slave": "001-04"
},
{
    "master": "002",
    "slave": "002-01"
},
{
    "master": "002",
    "slave": "002-02"
},
{
    "master": "002",
    "slave": "002-03"
},
{
    "master": "003",
    "slave": "003-01"
},
{
    "master": "003",
    "slave": "003-02"
},
{
    "master": "003",
    "slave": "003-03"
},
{
    "master": "003",
    "slave": "003-04"
},
{
    "master": "003",
    "slave": "003-05"
}
]